MANIFEST.in
README.md
setup.cfg
setup.py
docassemble/__init__.py
docassemble.MAPovertyScale.egg-info/PKG-INFO
docassemble.MAPovertyScale.egg-info/SOURCES.txt
docassemble.MAPovertyScale.egg-info/dependency_links.txt
docassemble.MAPovertyScale.egg-info/namespace_packages.txt
docassemble.MAPovertyScale.egg-info/not-zip-safe
docassemble.MAPovertyScale.egg-info/top_level.txt
docassemble/MAPovertyScale/__init__.py
docassemble/MAPovertyScale/data/questions/poverty.yml
docassemble/MAPovertyScale/data/sources/README.md
docassemble/MAPovertyScale/data/static/README.md
docassemble/MAPovertyScale/data/templates/README.md