Metadata-Version: 2.1
Name: docassemble.MAPovertyScale
Version: 0.0.2
Summary: Contains most recent poverty scale in poverty.yml
Home-page: https://docassemble.org
Author: System Administrator
Author-email: qsteenhuis@suffolk.edu
License: The MIT License (MIT)
Platform: UNKNOWN
